PyDBOD/__init__.py
PyDBOD/base.py
PyDBOD/kdist.py
PyDBOD/ldof.py
PyDBOD/load.py
PyDBOD/lof.py
PyDBOD/loop.py
PyDBOD/meandist.py
PyDBOD/odin.py
PyDBOD/outres.py
PyDBOD/pinn_lof.py
PyDBOD-1.1.dist-info/LICENSE.txt
PyDBOD-1.1.dist-info/METADATA
PyDBOD-1.1.dist-info/WHEEL
PyDBOD-1.1.dist-info/top_level.txt
PyDBOD-1.1.dist-info/RECORD
