Metadata-Version: 2.1
Name: PyDBOD
Version: 1.1
Summary: A Distances Based Outlier Detector package
Home-page: https://github.com/miki97/TFG-OutlierDetection
Author: Miguel Ángel López Robles
License: Licencia pública general de GNU Versión 3
Platform: UNKNOWN
